pgpd/__init__.py
pgpd/_accessor_dataframe.py
pgpd/_accessor_series.py
pgpd/_array.py
pgpd/_delegated_dataframe.py
pgpd/_delegated_series.py
pgpd/_util.py
pgpd/_version.py
pgpd-3.0.4.dist-info/METADATA
pgpd-3.0.4.dist-info/WHEEL
pgpd-3.0.4.dist-info/top_level.txt
pgpd-3.0.4.dist-info/RECORD
