Metadata-Version: 2.1
Name: pgpd
Version: 3.0.4
Summary: Shapely ExtensionArray for pandas
Author: 0phoff
Requires-Dist: pandas >=1.1
Requires-Dist: shapely >=2.0.0
